apachescan/__init__.py
apachescan/__version__.py
apachescan/controller.py
apachescan/daemon.py
apachescan/exceptions.py
apachescan/analyzer/__init__.py
apachescan/analyzer/core.py
apachescan/guard/__init__.py
apachescan/guard/core.py
apachescan/parser/__init__.py
apachescan/parser/apache.py
apachescan/reader/__init__.py
apachescan/reader/filehandler.py
apachescan-0.1.0.dist-info/METADATA
apachescan-0.1.0.dist-info/WHEEL
apachescan-0.1.0.dist-info/entry_points.txt
apachescan-0.1.0.dist-info/top_level.txt
apachescan-0.1.0.dist-info/RECORD
